pip_test1008.py
pip_test1008-1.0.dist-info/LICENSE.lic
pip_test1008-1.0.dist-info/METADATA
pip_test1008-1.0.dist-info/WHEEL
pip_test1008-1.0.dist-info/top_level.txt
pip_test1008-1.0.dist-info/RECORD
