Metadata-Version: 2.1
Name: pip-test1008
Version: 1.0
Summary: A  module for test
Author: zenghui_shu
Author-email: zenghui_shu@163.com
License: MIT
License-File: LICENSE.lic
